okchain1_docs_theme-0.1.43-py3.7-nspkg.pth
okchain1/theme/__init__.py
okchain1/theme/rtd/__init__.py
okchain1/theme/rtd/conf/__init__.py
okchain1/theme/rtd/conf/clients_admin_ui.py
okchain1/theme/rtd/conf/clients_crash.py
okchain1/theme/rtd/conf/clients_dbal.py
okchain1/theme/rtd/conf/clients_java.py
okchain1/theme/rtd/conf/clients_jdbc.py
okchain1/theme/rtd/conf/clients_mesos.py
okchain1/theme/rtd/conf/clients_npgsql.py
okchain1/theme/rtd/conf/clients_pdo.py
okchain1/theme/rtd/conf/clients_python.py
okchain1/theme/rtd/conf/clients_ruby.py
okchain1/theme/rtd/conf/cloud_cli.py
okchain1/theme/rtd/conf/cloud_console.py
okchain1/theme/rtd/conf/cloud_getting_started.py
okchain1/theme/rtd/conf/cloud_iot.py
okchain1/theme/rtd/conf/crate_getting_started.py
okchain1/theme/rtd/conf/crate_guide.py
okchain1/theme/rtd/conf/crate_reference.py
okchain1/theme/rtd/conf/okchain_docs.py
okchain1/theme/rtd/conf/okchain_oips.py
okchain1/theme/rtd/conf/sql_99.py
okchain1/theme/rtd/conf/standalone.py
okchain1/theme/rtd/okchain1/base.html
okchain1/theme/rtd/okchain1/community.html
okchain1/theme/rtd/okchain1/footer.html
okchain1/theme/rtd/okchain1/globaltoc.html
okchain1/theme/rtd/okchain1/layout.html
okchain1/theme/rtd/okchain1/layoutpage.html
okchain1/theme/rtd/okchain1/localtoc.html
okchain1/theme/rtd/okchain1/navbar.html
okchain1/theme/rtd/okchain1/navbarsearchbox.html
okchain1/theme/rtd/okchain1/navbartoc.html
okchain1/theme/rtd/okchain1/relations.html
okchain1/theme/rtd/okchain1/search.html
okchain1/theme/rtd/okchain1/searchbox.html
okchain1/theme/rtd/okchain1/searchresults.html
okchain1/theme/rtd/okchain1/sidebar.html
okchain1/theme/rtd/okchain1/sidebartoc.html
okchain1/theme/rtd/okchain1/sourcelink.html
okchain1/theme/rtd/okchain1/theme.conf
okchain1/theme/rtd/okchain1/static/css/bootstrap.css
okchain1/theme/rtd/okchain1/static/css/community.css
okchain1/theme/rtd/okchain1/static/css/components.css
okchain1/theme/rtd/okchain1/static/css/custom.css
okchain1_docs_theme-0.1.43.dist-info/LICENSE
okchain1_docs_theme-0.1.43.dist-info/METADATA
okchain1_docs_theme-0.1.43.dist-info/NOTICE
okchain1_docs_theme-0.1.43.dist-info/WHEEL
okchain1_docs_theme-0.1.43.dist-info/namespace_packages.txt
okchain1_docs_theme-0.1.43.dist-info/top_level.txt
okchain1_docs_theme-0.1.43.dist-info/RECORD
