Metadata-Version: 2.1
Name: okchain1-docs-theme
Version: 0.1.43
Summary: OKC Docs Theme
Home-page: https://github.com/zccst/crate-docs-theme
Author: OKC
Author-email: okchain@okg.com
License: Apache License 2.0
Keywords: OKC docs sphinx readthedocs
Platform: UNKNOWN
Classifier: Intended Audience :: Developers
Classifier: License :: OSI Approved :: Apache Software License
Classifier: Operating System :: OS Independent
Classifier: Programming Language :: Python
Classifier: Programming Language :: Python :: 3
Classifier: Programming Language :: Python :: 3.6
Classifier: Programming Language :: Python :: 3.7
Classifier: Topic :: Software Development :: Documentation
Requires-Python: >=3.7
Requires-Dist: sphinxcontrib-plantuml (==0.14)
Requires-Dist: sphinx-sitemap (==0.3.1)
